pyplnoise.py
pyplnoise-1.4.dist-info/LICENSE
pyplnoise-1.4.dist-info/METADATA
pyplnoise-1.4.dist-info/WHEEL
pyplnoise-1.4.dist-info/top_level.txt
pyplnoise-1.4.dist-info/RECORD
