Metadata-Version: 2.1
Name: pyplnoise
Version: 1.4
Summary: Arbitrarily long streams of power law noise using NumPy and SciPy.
Home-page: https://github.com/janwaldmann/pyplnoise
Author: Jan Waldmann
Author-email: dev@pgmail.org
License: BSD
Classifier: Programming Language :: Python :: 3
Classifier: License :: OSI Approved :: BSD License
Classifier: Operating System :: OS Independent
Classifier: Development Status :: 7 - Inactive
Classifier: Intended Audience :: Developers
Classifier: Topic :: Scientific/Engineering :: Physics
Classifier: Topic :: Scientific/Engineering :: Information Analysis
Requires-Python: >=3.7,<3.99
License-File: LICENSE
Requires-Dist: numpy (>=1.17.0)
Requires-Dist: scipy (>=1.3.0)
